turtlemd/__init__.py
turtlemd/integrators.py
turtlemd/potentials/__init__.py
turtlemd/potentials/lennardjones.py
turtlemd/potentials/potential.py
turtlemd/potentials/well.py
turtlemd/py.typed
turtlemd/simulation/__init__.py
turtlemd/simulation/mdsimulation.py
turtlemd/simulation/stopping.py
turtlemd/system/__init__.py
turtlemd/system/box.py
turtlemd/system/particles.py
turtlemd/system/system.py
turtlemd/tools/__init__.py
turtlemd/tools/tools.py
turtlemd/tools/xyz.py
turtlemd/version.py
turtlemd-2023.3.1.dist-info/LICENSE
turtlemd-2023.3.1.dist-info/METADATA
turtlemd-2023.3.1.dist-info/WHEEL
turtlemd-2023.3.1.dist-info/RECORD
