Metadata-Version: 2.1
Name: turtlemd
Version: 2023.3.1
Summary: A slow molecular dynamics library for testing
License: MIT
Author: Anders Lervik
Author-email: andersle@gmail.com
Requires-Python: >=3.10,<4.0
Classifier: License :: OSI Approved :: MIT License
Classifier: Programming Language :: Python :: 3
Classifier: Programming Language :: Python :: 3.10
Classifier: Programming Language :: Python :: 3.11
Requires-Dist: numpy (>=1.24.2,<2.0.0)
